{"match_id": "b6d86df4-2c67-42bd-a6bb-6000eedc0aec.nakama-0", "map": "AmbroseValley", "date": "2026-02-13", "players": [{"id": "a8215cdf-ba5b-42b6-8b87-7381c3231ba6", "is_bot": false, "path": [{"x": 267.83, "z": -48.3, "t": 0}, {"x": 250.14, "z": -60.14, "t": 20}, {"x": 235.52, "z": -69.73, "t": 26}, {"x": 242.08, "z": -54.18, "t": 31}, {"x": 257.54, "z": -60.83, "t": 36}, {"x": 242.06, "z": -64.1, "t": 41}, {"x": 233.45, "z": -78.21, "t": 46}, {"x": 221.63, "z": -92.73, "t": 51}, {"x": 217.47, "z": -106.02, "t": 56}, {"x": 213.26, "z": -92.61, "t": 61}, {"x": 200.74, "z": -79.4, "t": 66}, {"x": 193.6, "z": -74.37, "t": 71}, {"x": 186.22, "z": -81.63, "t": 76}, {"x": 185.64, "z": -86.59, "t": 81}, {"x": 189.79, "z": -78.18, "t": 86}, {"x": 198.65, "z": -78.38, "t": 91}, {"x": 185.5, "z": -80.98, "t": 96}, {"x": 178.58, "z": -87.53, "t": 101}, {"x": 162.39, "z": -97.45, "t": 106}, {"x": 152.65, "z": -92.56, "t": 111}, {"x": 148.89, "z": -90.0, "t": 116}, {"x": 158.32, "z": -88.43, "t": 121}, {"x": 149.42, "z": -99.24, "t": 126}, {"x": 139.86, "z": -89.57, "t": 131}, {"x": 150.21, "z": -89.85, "t": 136}, {"x": 153.26, "z": -95.55, "t": 141}, {"x": 149.26, "z": -90.96, "t": 146}, {"x": 139.79, "z": -79.93, "t": 151}, {"x": 144.98, "z": -68.05, "t": 156}, {"x": 154.57, "z": -73.45, "t": 161}, {"x": 147.01, "z": -78.88, "t": 166}, {"x": 133.88, "z": -66.44, "t": 171}, {"x": 112.3, "z": -61.66, "t": 176}, {"x": 104.08, "z": -56.95, "t": 181}, {"x": 103.49, "z": -67.07, "t": 186}, {"x": 96.46, "z": -83.75, "t": 191}, {"x": 95.39, "z": -86.52, "t": 197}, {"x": 88.08, "z": -84.03, "t": 202}, {"x": 83.02, "z": -97.46, "t": 207}, {"x": 81.36, "z": -91.49, "t": 212}, {"x": 83.57, "z": -73.35, "t": 217}, {"x": 84.08, "z": -75.57, "t": 222}, {"x": 86.06, "z": -90.53, "t": 227}, {"x": 99.25, "z": -89.67, "t": 232}, {"x": 87.25, "z": -77.35, "t": 237}, {"x": 91.71, "z": -78.24, "t": 242}, {"x": 96.34, "z": -82.08, "t": 247}, {"x": 100.05, "z": -82.07, "t": 252}, {"x": 108.07, "z": -78.94, "t": 257}, {"x": 113.04, "z": -66.71, "t": 262}, {"x": 127.36, "z": -67.01, "t": 267}, {"x": 130.65, "z": -61.64, "t": 277}, {"x": 144.28, "z": -68.12, "t": 282}, {"x": 158.25, "z": -71.7, "t": 287}, {"x": 161.83, "z": -83.05, "t": 292}, {"x": 158.92, "z": -92.66, "t": 297}, {"x": 162.42, "z": -81.2, "t": 302}, {"x": 160.61, "z": -72.08, "t": 307}, {"x": 158.87, "z": -72.69, "t": 317}, {"x": 154.33, "z": -74.05, "t": 322}, {"x": 137.12, "z": -68.28, "t": 337}, {"x": 134.13, "z": -79.11, "t": 342}, {"x": 129.37, "z": -78.67, "t": 347}, {"x": 129.45, "z": -65.73, "t": 352}, {"x": 131.93, "z": -63.73, "t": 362}, {"x": 130.23, "z": -58.32, "t": 373}, {"x": 134.36, "z": -49.21, "t": 383}, {"x": 124.65, "z": -51.92, "t": 388}, {"x": 117.76, "z": -57.87, "t": 393}, {"x": 108.79, "z": -58.99, "t": 403}, {"x": 104.53, "z": -55.03, "t": 408}, {"x": 107.61, "z": -59.55, "t": 413}, {"x": 109.04, "z": -79.09, "t": 418}, {"x": 99.2, "z": -84.27, "t": 423}, {"x": 95.62, "z": -85.83, "t": 428}, {"x": 94.27, "z": -77.02, "t": 433}, {"x": 99.74, "z": -67.26, "t": 438}, {"x": 100.26, "z": -57.74, "t": 443}, {"x": 107.51, "z": -57.93, "t": 448}, {"x": 111.54, "z": -73.69, "t": 453}, {"x": 110.16, "z": -88.45, "t": 458}, {"x": 110.07, "z": -94.15, "t": 463}, {"x": 125.26, "z": -97.8, "t": 468}, {"x": 130.7, "z": -80.84, "t": 473}, {"x": 132.36, "z": -64.7, "t": 478}, {"x": 133.03, "z": -69.03, "t": 498}, {"x": 128.93, "z": -65.75, "t": 503}, {"x": 132.24, "z": -67.63, "t": 513}, {"x": 136.06, "z": -70.93, "t": 518}, {"x": 136.04, "z": -75.48, "t": 528}, {"x": 138.9, "z": -80.66, "t": 538}, {"x": 127.31, "z": -69.52, "t": 574}, {"x": 128.72, "z": -62.93, "t": 579}, {"x": 119.8, "z": -68.56, "t": 584}, {"x": 104.57, "z": -54.88, "t": 589}, {"x": 92.6, "z": -51.95, "t": 594}, {"x": 88.11, "z": -44.76, "t": 599}, {"x": 74.27, "z": -49.03, "t": 604}, {"x": 60.99, "z": -40.49, "t": 609}, {"x": 58.56, "z": -41.16, "t": 624}, {"x": 52.2, "z": -39.01, "t": 634}, {"x": 57.36, "z": -41.9, "t": 639}, {"x": 62.3, "z": -43.29, "t": 644}, {"x": 52.68, "z": -38.91, "t": 649}, {"x": 47.36, "z": -44.9, "t": 659}, {"x": 35.37, "z": -45.42, "t": 664}, {"x": 15.67, "z": -52.23, "t": 669}, {"x": 12.7, "z": -54.62, "t": 674}, {"x": 18.5, "z": -50.17, "t": 679}, {"x": 21.56, "z": -51.26, "t": 684}, {"x": 28.32, "z": -50.03, "t": 694}, {"x": 30.45, "z": -47.43, "t": 699}, {"x": 31.02, "z": -44.46, "t": 704}, {"x": 29.49, "z": -40.47, "t": 709}, {"x": 28.51, "z": -36.77, "t": 714}, {"x": 26.72, "z": -31.12, "t": 724}]}], "events": [{"type": "loot", "x": 186.22, "z": -81.63, "t": 76, "player_id": "a8215cdf-ba5b-42b6-8b87-7381c3231ba6"}, {"type": "loot", "x": 151.8, "z": -91.69, "t": 111, "player_id": "a8215cdf-ba5b-42b6-8b87-7381c3231ba6"}, {"type": "loot", "x": 147.94, "z": -89.24, "t": 117, "player_id": "a8215cdf-ba5b-42b6-8b87-7381c3231ba6"}, {"type": "loot", "x": 150.21, "z": -89.85, "t": 136, "player_id": "a8215cdf-ba5b-42b6-8b87-7381c3231ba6"}, {"type": "loot", "x": 147.01, "z": -78.88, "t": 165, "player_id": "a8215cdf-ba5b-42b6-8b87-7381c3231ba6"}, {"type": "loot", "x": 106.43, "z": -58.52, "t": 178, "player_id": "a8215cdf-ba5b-42b6-8b87-7381c3231ba6"}, {"type": "loot", "x": 106.43, "z": -58.52, "t": 179, "player_id": "a8215cdf-ba5b-42b6-8b87-7381c3231ba6"}, {"type": "loot", "x": 96.06, "z": -88.46, "t": 198, "player_id": "a8215cdf-ba5b-42b6-8b87-7381c3231ba6"}, {"type": "loot", "x": 87.3, "z": -77.05, "t": 238, "player_id": "a8215cdf-ba5b-42b6-8b87-7381c3231ba6"}, {"type": "loot", "x": 91.71, "z": -78.24, "t": 242, "player_id": "a8215cdf-ba5b-42b6-8b87-7381c3231ba6"}, {"type": "loot", "x": 161.77, "z": -69.56, "t": 310, "player_id": "a8215cdf-ba5b-42b6-8b87-7381c3231ba6"}, {"type": "loot", "x": 159.16, "z": -75.27, "t": 315, "player_id": "a8215cdf-ba5b-42b6-8b87-7381c3231ba6"}, {"type": "loot", "x": 104.53, "z": -55.03, "t": 408, "player_id": "a8215cdf-ba5b-42b6-8b87-7381c3231ba6"}, {"type": "loot", "x": 95.47, "z": -85.22, "t": 429, "player_id": "a8215cdf-ba5b-42b6-8b87-7381c3231ba6"}, {"type": "loot", "x": 128.37, "z": -63.05, "t": 577, "player_id": "a8215cdf-ba5b-42b6-8b87-7381c3231ba6"}, {"type": "loot", "x": 128.37, "z": -63.05, "t": 578, "player_id": "a8215cdf-ba5b-42b6-8b87-7381c3231ba6"}, {"type": "loot", "x": 129.64, "z": -62.29, "t": 580, "player_id": "a8215cdf-ba5b-42b6-8b87-7381c3231ba6"}, {"type": "loot", "x": 129.64, "z": -62.29, "t": 580, "player_id": "a8215cdf-ba5b-42b6-8b87-7381c3231ba6"}, {"type": "kill", "x": 57.34, "z": -42.5, "t": 628, "player_id": "a8215cdf-ba5b-42b6-8b87-7381c3231ba6"}, {"type": "loot", "x": 48.55, "z": -34.96, "t": 651, "player_id": "a8215cdf-ba5b-42b6-8b87-7381c3231ba6"}, {"type": "kill", "x": 16.61, "z": -54.14, "t": 675, "player_id": "a8215cdf-ba5b-42b6-8b87-7381c3231ba6"}, {"type": "loot", "x": 18.19, "z": -51.31, "t": 681, "player_id": "a8215cdf-ba5b-42b6-8b87-7381c3231ba6"}, {"type": "storm_death", "x": 26.61, "z": -30.41, "t": 725, "player_id": "a8215cdf-ba5b-42b6-8b87-7381c3231ba6"}]}